[
    {
      "name": "socials",
      "icon": "ph:heart",
    	"items": [
        {
          "platform": "github",
          "name": "Github",
          "user": "@pow4you",
          "link": "https://github.com/pow4you",
          "img": "/assets/images/github.png",
          "description": "Pow4you on Github. There you can find whatever I'm currently working on, what I'm learning and what I'm trying get better at.",
          "icon": "fa6-brands:github",
          "spotlight":true
        },
        {
          "platform": "discord",
          "name": "Discord",
          "user": "@PowowoCat",
          "link": "https://discord.com/users/powowocat",
          "img": "/assets/images/discord.webp",
          "description": "Connect with me on Discord.",
          "icon": "fa6-brands:discord",
          "spotlight":true
        },
        {
          "platform": "instagram",
          "name": "Cosplay Instagram",
          "user": "@PowCosplay",
          "img": false,
          "link": "https://instagram.com/powcosplay",
          "description": "Follow my cosplay journey on Instagram.",
          "icon": "fa6-brands:instagram",
          "spotlight":true
        },
        {
          "platform": "tumblr",
          "name": "Tumblr",
          "user": "@powowo",
          "img": "/assets/images/tumblr.webp",
          "link": "https://www.tumblr.com/powowo",
          "description": "Friendly blog, I don't really use that often...",
          "icon": "fa6-brands:tumblr"
        },
        {
          "platform": "tiktok",
          "name": "TikTok",
          "user": "@https51",
          "img": "/assets/images/tiktok.webp",
          "link": "https://www.tiktok.com/@https51",
          "description": "This is my TikTok Profile, where I post all sorts of skits and videos.",
          "icon": "fa6-brands:tiktok"
        },
        {
          "platform": "youtube",
          "name": "YouTube",
          "user": "@powcat",
          "img": false,
          "link": "https://www.youtube.com/@powcat",
          "description": "This is my creative outlet. Most of what's on this channel is music, but I'll occasionally also post YTPs, memes and parodies.",
          "icon": "fa6-brands:youtube"
        },
        {
          "platform": "steam",
          "name": "Steam",
          "user": "@nghariad",
          "img": false,
          "link": "https://steamcommunity.com/profiles/76561198202404092",
          "description": "",
          "icon": "fa6-brands:steam"
        }
      ]
    },
    {
      "name":"links",
      "icon":"ph:link",
      "items":[
        {
          "platform": "coming soon",
          "name": "Coming Soon",
          "user": null,
          "link": "https://soon.pow.gay",
          "img": null,
          "description": "Overview page for webprojects I'm currently working on or have already finished. 🛠️",
          "icon": "noto:building-construction",
          "spotlight":true
        }
      ]
    }
]

